uwp_injector.py
uwp_injector-0.1.0.dist-info/LICENSE
uwp_injector-0.1.0.dist-info/METADATA
uwp_injector-0.1.0.dist-info/WHEEL
uwp_injector-0.1.0.dist-info/top_level.txt
uwp_injector-0.1.0.dist-info/RECORD
