Metadata-Version: 2.1
Name: uwp-injector
Version: 0.1.0
Summary: A tool to inject DLLs into UWP applications
Author-email: Olivia Ryan <olivia.r.dev@gmail.com>
License: MIT License
Project-URL: Repository, https://github.com/olivi-r/uwp-injector
Project-URL: Issues, https://github.com/olivi-r/uwp-injector/issues
Classifier: Development Status :: 4 - Beta
Classifier: Intended Audience :: Developers
Classifier: License :: OSI Approved :: MIT License
Classifier: Programming Language :: Python :: 3
License-File: LICENSE
Requires-Dist: psutil
Requires-Dist: pywin32
